[
  {
    "id": 1,
    "name": "Séance spéciale",
    "color": "#00FFFF"
  },
  {
    "id": 2,
    "name": "Volet professionnel",
    "color": "#00FFFF"
  },
  {
    "id": 3,
    "name": "Séance scolaire",
    "color": "#00FFFF"
  },
  {
    "id": 4,
    "name": "Compétition et sélections",
    "color": "#00FFFF"
  },
  {
    "id": 5,
    "name": "Long métrage et rencontres",
    "color": "#00FFFF"
  },
  {
    "id": 6,
    "name": "Atelier secret Fab",
    "color": "#00FFFF"
  },
  {
    "id": 7,
    "name": "Salon des nouvelles écritures",
    "color": "#00FFFF"
  },
  {
    "id": 8,
    "name": "Unknown",
    "color": "#00FFFF"
  }
]
